README.rst
setup.py
miniuri/__init__.py
miniuri/miniuri.py
miniuri.egg-info/PKG-INFO
miniuri.egg-info/SOURCES.txt
miniuri.egg-info/dependency_links.txt
miniuri.egg-info/top_level.txt
miniuri/tests/__init__.py
miniuri/tests/test_miniuri.py